lab_space/__init__.py
lab_space/analysis.py
lab_space/dataspace.py
lab_space/experiment.py
lab_space/file_utils.py
lab_space/labspace.py
lab_space/test.py
lab_space/config/analysis/analysis_config.json
lab_space/config/core/core.json
lab_space/config/core/core_default.json
lab_space/config/expt/expt_config.json
lab_space/config/trial/trial_config.json
lab_space/results/data.csv
lab_space/scripts/__init__.py
lab_space/scripts/add_cli.bash
lab_space/scripts/setup_core.py
lab_space-1.0.1.dist-info/LICENSE
lab_space-1.0.1.dist-info/METADATA
lab_space-1.0.1.dist-info/WHEEL
lab_space-1.0.1.dist-info/top_level.txt
lab_space-1.0.1.dist-info/RECORD
