Metadata-Version: 2.1
Name: lab-space
Version: 1.0.1
Summary: The purpose of this project is to provide a user friendly pipeline for defining and running experiments.
Author-email: "Jared J. Beard" <jbeard6@mix.wvu.edu>
Project-URL: Homepage, https://github.com/jaredjbeard/lab-space
Project-URL: Documentation, https://lab-space.readthedocs.io/en/latest/introduction.html
Classifier: Programming Language :: Python :: 3
Classifier: License :: OSI Approved :: BSD License
Classifier: Operating System :: OS Independent
Requires-Python: >=3.7
License-File: LICENSE
